rvdata/__init__.py
rvdata/rvdata.py
rvdata-0.1.0.dist-info/LICENSE.rst
rvdata-0.1.0.dist-info/WHEEL
rvdata-0.1.0.dist-info/METADATA
rvdata-0.1.0.dist-info/RECORD
