Metadata-Version: 2.1
Name: rvdata
Version: 0.1.0
Summary: Radial Velocity Data
Home-page: https://github.com/j-faria/rvdata
Keywords: rvdata
Author: João Faria
Author-email: joao.faria@astro.up.pt
Requires-Python: >=3.7,<3.11
Classifier: Development Status :: 2 - Pre-Alpha
Classifier: Intended Audience :: Developers
Classifier: License :: OSI Approved :: MIT License
Classifier: Natural Language :: English
Classifier: Programming Language :: Python :: 3
Classifier: Programming Language :: Python :: 3.10
Classifier: Programming Language :: Python :: 3.7
Classifier: Programming Language :: Python :: 3.8
Classifier: Programming Language :: Python :: 3.9
Project-URL: Bug Tracker, https://github.com/j-faria/rvdata/issues
Project-URL: Documentation, https://rvdata.readthedocs.io
Project-URL: Repository, https://github.com/j-faria/rvdata
